personalcolor.py
personalcolor-0.0.1.dist-info/METADATA
personalcolor-0.0.1.dist-info/WHEEL
personalcolor-0.0.1.dist-info/entry_points.txt
personalcolor-0.0.1.dist-info/top_level.txt
personalcolor-0.0.1.dist-info/RECORD
