Metadata-Version: 2.1
Name: personalcolor
Version: 0.0.1
Summary: Shows your personal color
Home-page: https://github.com/harunearakage/personalcolor
Author: harune arakage
Author-email: s2122002@stu.musashino-u.ac.jp
License: UNKNOWN
Project-URL: Bug Tracker, https://github.com/harunearakage/personalcolor
Platform: UNKNOWN
Classifier: Programming Language :: Python :: 3
Classifier: License :: OSI Approved :: MIT License
Classifier: Operating System :: OS Independent
Requires-Python: >=3.7
